pixeldb/__init__.py
pixeldb-1.1.3.dist-info/WHEEL
pixeldb-1.1.3.dist-info/METADATA
pixeldb-1.1.3.dist-info/RECORD
